README.rst
setup.py
tallinja/__init__.py
tallinja/balance.py
tallinja/balance_cli.py
tallinja_balance.egg-info/PKG-INFO
tallinja_balance.egg-info/SOURCES.txt
tallinja_balance.egg-info/dependency_links.txt
tallinja_balance.egg-info/entry_points.txt
tallinja_balance.egg-info/requires.txt
tallinja_balance.egg-info/top_level.txt