Metadata-Version: 1.1
Name: tallinja-balance
Version: 1.0.0
Summary: Balance check for Tallinja (Malta) public transport cards
Home-page: https://github.com/dottedmag/tallinja-balance
Author: Mikhail Gusarov
Author-email: dottedmag@dottedmag.net
License: MIT
Keywords: malta tallinja transport
Platform: UNKNOWN
Classifier: Development Status :: 5 - Production/Stable
Classifier: Environment :: Console
Classifier: Intended Audience :: End Users/Desktop
Classifier: License :: OSI Approved :: MIT License
Classifier: Operating System :: OS Independent
Classifier: Topic :: Utilities
